LICENSE
README.md
pyproject.toml
setup.py
bromine/__init__.py
bromine/browser.py
bromine/django_admin.py
bromine/pytest.py
bromine/select2.py
gambit_bromine.egg-info/PKG-INFO
gambit_bromine.egg-info/SOURCES.txt
gambit_bromine.egg-info/dependency_links.txt
gambit_bromine.egg-info/entry_points.txt
gambit_bromine.egg-info/requires.txt
gambit_bromine.egg-info/top_level.txt