Metadata-Version: 2.1
Name: gambit-bromine
Version: 0.4.3
Summary: Pythonic web testing
Home-page: https://github.com/dvarrazzo/bromine
Author: Daniele Varrazzo
Author-email: daniele.varrazzo@gmail.com
License: UNKNOWN
Platform: UNKNOWN
Classifier: Development Status :: 4 - Beta
Classifier:         Framework :: Pytest
Classifier:         Intended Audience :: Developers
Classifier:         License :: OSI Approved :: MIT License
Classifier:         Operating System :: OS Independent
Classifier:         Programming Language :: Python :: 3
Classifier:         Topic :: Internet :: WWW/HTTP :: Browsers
Classifier:         Topic :: Software Development :: Testing
Requires-Python: >=3.8
License-File: LICENSE
